{
  "timestamp": 1740708255955,
  "lastUpdate": "2025-02-28 10:04:15",
  "data": [
    {
      "id": "101010100",
      "province": "北京",
      "city": "北京",
      "realtime": {
        "nameen": "beijing",
        "cityname": "北京",
        "city": "101010100",
        "temp": "10.2",
        "tempf": "50.4",
        "WD": "东风",
        "wde": "E",
        "WS": "1级",
        "wse": "4km/h",
        "SD": "32%",
        "sd": "32%",
        "qy": "1012",
        "njd": "4km",
        "time": "09:55",
        "rain": "0",
        "rain24h": "0",
        "aqi": "144",
        "aqi_pm25": "144",
        "weather": "霾",
        "weathere": "haze",
        "weathercode": "d53",
        "limitnumber": "1和6",
        "date": "02月28日(星期五)"
      },
      "weather": {
        "day": {
          "date": "28日白天",
          "weather": "晴",
          "temp": "17",
          "tempUnit": "°C",
          "wind": {
            "direction": "东南风",
            "directionCode": "SE",
            "level": "<3级"
          },
          "sunrise": "日出 06:50"
        },
        "night": {
          "date": "28日夜间",
          "weather": "多云",
          "temp": "3",
          "tempUnit": "°C",
          "wind": {
            "direction": "东北风",
            "directionCode": "NE",
            "level": "<3级"
          },
          "sunset": "日落 18:03"
        }
      }
    },
    {
      "id": "101020100",
      "province": "上海",
      "city": "上海",
      "realtime": {
        "nameen": "shanghai",
        "cityname": "上海",
        "city": "101020100",
        "temp": "15",
        "tempf": "59",
        "WD": "北风",
        "wde": "N",
        "WS": "1级",
        "wse": "3km/h",
        "SD": "82%",
        "sd": "82%",
        "qy": "1019",
        "njd": "5km",
        "time": "09:50",
        "rain": "0",
        "rain24h": "0",
        "aqi": "43",
        "aqi_pm25": "43",
        "weather": "霾",
        "weathere": "haze",
        "weathercode": "d53",
        "limitnumber": "",
        "date": "02月28日(星期五)"
      },
      "weather": {
        "day": {
          "date": "28日白天",
          "weather": "晴",
          "temp": "20",
          "tempUnit": "°C",
          "wind": {
            "direction": "无持续风向",
            "directionCode": "NNW",
            "level": "<3级"
          },
          "sunrise": "日出 06:22"
        },
        "night": {
          "date": "28日夜间",
          "weather": "晴",
          "temp": "12",
          "tempUnit": "°C",
          "wind": {
            "direction": "无持续风向",
            "directionCode": "NNW",
            "level": "<3级"
          },
          "sunset": "日落 17:50"
        }
      }
    },
    {
      "id": "101030100",
      "province": "天津",
      "city": "天津",
      "realtime": {
        "nameen": "tianjin",
        "cityname": "天津",
        "city": "101030100",
        "temp": "11.1",
        "tempf": "52",
        "WD": "西南风",
        "wde": "SW",
        "WS": "2级",
        "wse": "6km/h",
        "SD": "55%",
        "sd": "55%",
        "qy": "1016",
        "njd": "3km",
        "time": "09:50",
        "rain": "0",
        "rain24h": "0",
        "aqi": "237",
        "aqi_pm25": "237",
        "weather": "晴",
        "weathere": "Sunny",
        "weathercode": "d00",
        "limitnumber": "1和6",
        "date": "02月28日(星期五)"
      },
      "weather": {
        "day": {
          "date": "28日白天",
          "weather": "晴",
          "temp": "18",
          "tempUnit": "°C",
          "wind": {
            "direction": "东南风",
            "directionCode": "SE",
            "level": "<3级"
          },
          "sunrise": "日出 06:46"
        },
        "night": {
          "date": "28日夜间",
          "weather": "多云",
          "temp": "7",
          "tempUnit": "°C",
          "wind": {
            "direction": "东南风",
            "directionCode": "SE",
            "level": "<3级"
          },
          "sunset": "日落 18:01"
        }
      }
    },
    {
      "id": "101040100",
      "province": "重庆",
      "city": "重庆",
      "realtime": {
        "nameen": "chongqing",
        "cityname": "重庆",
        "city": "101040100",
        "temp": "14.8",
        "tempf": "58.6",
        "WD": "西北风",
        "wde": "NW",
        "WS": "1级",
        "wse": "1km/h",
        "SD": "59%",
        "sd": "59%",
        "qy": "983",
        "njd": "8km",
        "time": "09:50",
        "rain": "0",
        "rain24h": "0",
        "aqi": "67",
        "aqi_pm25": "67",
        "weather": "多云",
        "weathere": "Cloudy",
        "weathercode": "d01",
        "limitnumber": "5和0",
        "date": "02月28日(星期五)"
      },
      "weather": {
        "day": {
          "date": "28日白天",
          "weather": "多云",
          "temp": "21",
          "tempUnit": "°C",
          "wind": {
            "direction": "东北风",
            "directionCode": "NE",
            "level": "<3级"
          },
          "sunrise": "日出 07:21"
        },
        "night": {
          "date": "28日夜间",
          "weather": "多云",
          "temp": "12",
          "tempUnit": "°C",
          "wind": {
            "direction": "北风",
            "directionCode": "N",
            "level": "<3级"
          },
          "sunset": "日落 18:51"
        }
      }
    },
    {
      "id": "101050101",
      "province": "黑龙江",
      "city": "哈尔滨",
      "realtime": {
        "nameen": "haerbin",
        "cityname": "哈尔滨",
        "city": "101050101",
        "temp": "3.8",
        "tempf": "38.8",
        "WD": "西风",
        "wde": "W",
        "WS": "3级",
        "wse": "14km/h",
        "SD": "53%",
        "sd": "53%",
        "qy": "993",
        "njd": "13km",
        "time": "09:50",
        "rain": "0",
        "rain24h": "0",
        "aqi": "112",
        "aqi_pm25": "112",
        "weather": "晴",
        "weathere": "Sunny",
        "weathercode": "d00",
        "limitnumber": "",
        "date": "02月28日(星期五)"
      },
      "weather": {
        "day": {
          "date": "28日白天",
          "weather": "晴",
          "temp": "3",
          "tempUnit": "°C",
          "wind": {
            "direction": "西北风",
            "directionCode": "NW",
            "level": "4-5级"
          },
          "sunrise": "日出 06:15"
        },
        "night": {
          "date": "28日夜间",
          "weather": "多云",
          "temp": "-10",
          "tempUnit": "°C",
          "wind": {
            "direction": "东北风",
            "directionCode": "NE",
            "level": "3-4级"
          },
          "sunset": "日落 17:17"
        }
      }
    },
    {
      "id": "101060101",
      "province": "吉林",
      "city": "长春",
      "realtime": {
        "nameen": "changchun",
        "cityname": "长春",
        "city": "101060101",
        "temp": "5.9",
        "tempf": "42.6",
        "WD": "西风",
        "wde": "W",
        "WS": "4级",
        "wse": "27km/h",
        "SD": "64%",
        "sd": "64%",
        "qy": "983",
        "njd": "4km",
        "time": "09:50",
        "rain": "0",
        "rain24h": "0",
        "aqi": "143",
        "aqi_pm25": "143",
        "weather": "霾",
        "weathere": "haze",
        "weathercode": "d53",
        "limitnumber": "",
        "date": "02月28日(星期五)"
      },
      "weather": {
        "day": {
          "date": "28日白天",
          "weather": "晴",
          "temp": "9",
          "tempUnit": "°C",
          "wind": {
            "direction": "西南风",
            "directionCode": "SW",
            "level": "<3级"
          },
          "sunrise": "日出 06:18"
        },
        "night": {
          "date": "28日夜间",
          "weather": "多云",
          "temp": "-3",
          "tempUnit": "°C",
          "wind": {
            "direction": "东北风",
            "directionCode": "NE",
            "level": "<3级"
          },
          "sunset": "日落 17:24"
        }
      }
    },
    {
      "id": "101070101",
      "province": "辽宁",
      "city": "沈阳",
      "realtime": {
        "nameen": "shenyang",
        "cityname": "沈阳",
        "city": "101070101",
        "temp": "9",
        "tempf": "48.2",
        "WD": "西南风",
        "wde": "SW",
        "WS": "3级",
        "wse": "14km/h",
        "SD": "60%",
        "sd": "60%",
        "qy": "1009",
        "njd": "14km",
        "time": "09:55",
        "rain": "0",
        "rain24h": "0",
        "aqi": "124",
        "aqi_pm25": "124",
        "weather": "晴",
        "weathere": "Sunny",
        "weathercode": "d00",
        "limitnumber": "",
        "date": "02月28日(星期五)"
      },
      "weather": {
        "day": {
          "date": "28日白天",
          "weather": "晴",
          "temp": "12",
          "tempUnit": "°C",
          "wind": {
            "direction": "西南风",
            "directionCode": "SW",
            "level": "3-4级"
          },
          "sunrise": "日出 06:24"
        },
        "night": {
          "date": "28日夜间",
          "weather": "多云",
          "temp": "3",
          "tempUnit": "°C",
          "wind": {
            "direction": "东南风",
            "directionCode": "SE",
            "level": "<3级"
          },
          "sunset": "日落 17:33"
        }
      }
    },
    {
      "id": "101080101",
      "province": "内蒙古",
      "city": "呼和浩特",
      "realtime": {
        "nameen": "huhehaote",
        "cityname": "呼和浩特",
        "city": "101080101",
        "temp": "1.9",
        "tempf": "35.4",
        "WD": "西北风",
        "wde": "NW",
        "WS": "1级",
        "wse": "3km/h",
        "SD": "22%",
        "sd": "22%",
        "qy": "896",
        "njd": "22km",
        "time": "09:50",
        "rain": "0",
        "rain24h": "0",
        "aqi": "74",
        "aqi_pm25": "74",
        "weather": "晴",
        "weathere": "Sunny",
        "weathercode": "d00",
        "limitnumber": "",
        "date": "02月28日(星期五)"
      },
      "weather": {
        "day": {
          "date": "28日白天",
          "weather": "多云",
          "temp": "11",
          "tempUnit": "°C",
          "wind": {
            "direction": "西南风",
            "directionCode": "SW",
            "level": "<3级"
          },
          "sunrise": "日出 07:09"
        },
        "night": {
          "date": "28日夜间",
          "weather": "多云",
          "temp": "-6",
          "tempUnit": "°C",
          "wind": {
            "direction": "西南风",
            "directionCode": "SW",
            "level": "<3级"
          },
          "sunset": "日落 18:21"
        }
      }
    },
    {
      "id": "101090101",
      "province": "河北",
      "city": "石家庄",
      "realtime": {
        "nameen": "shijiazhuang",
        "cityname": "石家庄",
        "city": "101090101",
        "temp": "11.1",
        "tempf": "52",
        "WD": "南风",
        "wde": "S",
        "WS": "2级",
        "wse": "7km/h",
        "SD": "29%",
        "sd": "29%",
        "qy": "1005",
        "njd": "7km",
        "time": "09:55",
        "rain": "0",
        "rain24h": "0",
        "aqi": "128",
        "aqi_pm25": "128",
        "weather": "晴",
        "weathere": "Sunny",
        "weathercode": "d00",
        "limitnumber": "",
        "date": "02月28日(星期五)"
      },
      "weather": {
        "day": {
          "date": "28日白天",
          "weather": "晴",
          "temp": "19",
          "tempUnit": "°C",
          "wind": {
            "direction": "东南风",
            "directionCode": "SE",
            "level": "<3级"
          },
          "sunrise": "日出 06:56"
        },
        "night": {
          "date": "28日夜间",
          "weather": "多云",
          "temp": "3",
          "tempUnit": "°C",
          "wind": {
            "direction": "西北风",
            "directionCode": "NW",
            "level": "<3级"
          },
          "sunset": "日落 18:12"
        }
      }
    },
    {
      "id": "101100101",
      "province": "山西",
      "city": "太原",
      "realtime": {
        "nameen": "taiyuan",
        "cityname": "太原",
        "city": "101100101",
        "temp": "7.2",
        "tempf": "45",
        "WD": "北风",
        "wde": "N",
        "WS": "2级",
        "wse": "9km/h",
        "SD": "21%",
        "sd": "21%",
        "qy": "926",
        "njd": "19km",
        "time": "09:50",
        "rain": "0",
        "rain24h": "0",
        "aqi": "71",
        "aqi_pm25": "71",
        "weather": "多云",
        "weathere": "Cloudy",
        "weathercode": "d01",
        "limitnumber": "",
        "date": "02月28日(星期五)"
      },
      "weather": {
        "day": {
          "date": "28日白天",
          "weather": "多云",
          "temp": "16",
          "tempUnit": "°C",
          "wind": {
            "direction": "南风",
            "directionCode": "S",
            "level": "<3级"
          },
          "sunrise": "日出 07:04"
        },
        "night": {
          "date": "28日夜间",
          "weather": "多云",
          "temp": "-4",
          "tempUnit": "°C",
          "wind": {
            "direction": "西北风",
            "directionCode": "NW",
            "level": "<3级"
          },
          "sunset": "日落 18:20"
        }
      }
    },
    {
      "id": "101110101",
      "province": "陕西",
      "city": "西安",
      "realtime": {
        "nameen": "xian",
        "cityname": "西安",
        "city": "101110101",
        "temp": "9.6",
        "tempf": "49.3",
        "WD": "北风",
        "wde": "N",
        "WS": "1级",
        "wse": "2km/h",
        "SD": "61%",
        "sd": "61%",
        "qy": "967",
        "njd": "6km",
        "time": "09:50",
        "rain": "0",
        "rain24h": "0",
        "aqi": "113",
        "aqi_pm25": "113",
        "weather": "晴",
        "weathere": "Sunny",
        "weathercode": "d00",
        "limitnumber": "5和0",
        "date": "02月28日(星期五)"
      },
      "weather": {
        "day": {
          "date": "28日白天",
          "weather": "多云",
          "temp": "17",
          "tempUnit": "°C",
          "wind": {
            "direction": "无持续风向",
            "directionCode": "NNW",
            "level": "<3级"
          },
          "sunrise": "日出 07:15"
        },
        "night": {
          "date": "28日夜间",
          "weather": "多云",
          "temp": "6",
          "tempUnit": "°C",
          "wind": {
            "direction": "无持续风向",
            "directionCode": "NNW",
            "level": "<3级"
          },
          "sunset": "日落 18:38"
        }
      }
    },
    {
      "id": "101120101",
      "province": "山东",
      "city": "济南",
      "realtime": {
        "nameen": "jinan",
        "cityname": "济南",
        "city": "101120101",
        "temp": "16.7",
        "tempf": "62.1",
        "WD": "西南风",
        "wde": "SW",
        "WS": "1级",
        "wse": "3km/h",
        "SD": "48%",
        "sd": "48%",
        "qy": "996",
        "njd": "6km",
        "time": "09:50",
        "rain": "0",
        "rain24h": "0",
        "aqi": "122",
        "aqi_pm25": "122",
        "weather": "霾",
        "weathere": "haze",
        "weathercode": "d53",
        "limitnumber": "",
        "date": "02月28日(星期五)"
      },
      "weather": {
        "day": {
          "date": "28日白天",
          "weather": "多云",
          "temp": "22",
          "tempUnit": "°C",
          "wind": {
            "direction": "无持续风向",
            "directionCode": "NNW",
            "level": "<3级"
          },
          "sunrise": "日出 06:44"
        },
        "night": {
          "date": "28日夜间",
          "weather": "阴",
          "temp": "12",
          "tempUnit": "°C",
          "wind": {
            "direction": "无持续风向",
            "directionCode": "NNW",
            "level": "<3级"
          },
          "sunset": "日落 18:03"
        }
      }
    },
    {
      "id": "101130101",
      "province": "新疆",
      "city": "乌鲁木齐",
      "realtime": {
        "nameen": "wulumuqi",
        "cityname": "乌鲁木齐",
        "city": "101130101",
        "temp": "-3.6",
        "tempf": "25.5",
        "WD": "西北风",
        "wde": "NW",
        "WS": "1级",
        "wse": "3km/h",
        "SD": "92%",
        "sd": "92%",
        "qy": "911",
        "njd": "1km",
        "time": "09:55",
        "rain": "0",
        "rain24h": "0",
        "aqi": "108",
        "aqi_pm25": "108",
        "weather": "多云",
        "weathere": "Cloudy",
        "weathercode": "d01",
        "limitnumber": "",
        "date": "02月28日(星期五)"
      },
      "weather": {
        "day": {
          "date": "28日白天",
          "weather": "多云",
          "temp": "-2",
          "tempUnit": "°C",
          "wind": {
            "direction": "北风",
            "directionCode": "N",
            "level": "<3级"
          },
          "sunrise": "日出 08:49"
        },
        "night": {
          "date": "28日夜间",
          "weather": "多云",
          "temp": "-8",
          "tempUnit": "°C",
          "wind": {
            "direction": "西北风",
            "directionCode": "NW",
            "level": "<3级"
          },
          "sunset": "日落 19:55"
        }
      }
    },
    {
      "id": "101140101",
      "province": "西藏",
      "city": "拉萨",
      "realtime": {
        "nameen": "lasa",
        "cityname": "拉萨",
        "city": "101140101",
        "temp": "2.7",
        "tempf": "36.9",
        "WD": "东风",
        "wde": "E",
        "WS": "1级",
        "wse": "5km/h",
        "SD": "38%",
        "sd": "38%",
        "qy": "652",
        "njd": "7km",
        "time": "09:50",
        "rain": "0",
        "rain24h": "0",
        "aqi": "57",
        "aqi_pm25": "57",
        "weather": "霾",
        "weathere": "haze",
        "weathercode": "d53",
        "limitnumber": "",
        "date": "02月28日(星期五)"
      },
      "weather": {
        "day": {
          "date": "28日白天",
          "weather": "多云",
          "temp": "14",
          "tempUnit": "°C",
          "wind": {
            "direction": "无持续风向",
            "directionCode": "NNW",
            "level": "<3级"
          },
          "sunrise": "日出 08:23"
        },
        "night": {
          "date": "28日夜间",
          "weather": "多云",
          "temp": "-1",
          "tempUnit": "°C",
          "wind": {
            "direction": "南风",
            "directionCode": "S",
            "level": "3-4级"
          },
          "sunset": "日落 19:53"
        }
      }
    },
    {
      "id": "101150101",
      "province": "青海",
      "city": "西宁",
      "realtime": {
        "nameen": "xining",
        "cityname": "西宁",
        "city": "101150101",
        "temp": "-2.1",
        "tempf": "28.2",
        "WD": "西风",
        "wde": "W",
        "WS": "2级",
        "wse": "7km/h",
        "SD": "91%",
        "sd": "91%",
        "qy": "754",
        "njd": "5km",
        "time": "09:50",
        "rain": "0",
        "rain24h": "0",
        "aqi": "55",
        "aqi_pm25": "55",
        "weather": "雾",
        "weathere": "Foggy",
        "weathercode": "d18",
        "limitnumber": "",
        "date": "02月28日(星期五)"
      },
      "weather": {
        "day": {
          "date": "28日白天",
          "weather": "多云",
          "temp": "11",
          "tempUnit": "°C",
          "wind": {
            "direction": "无持续风向",
            "directionCode": "NNW",
            "level": "<3级"
          },
          "sunrise": "日出 07:45"
        },
        "night": {
          "date": "28日夜间",
          "weather": "阴",
          "temp": "-2",
          "tempUnit": "°C",
          "wind": {
            "direction": "无持续风向",
            "directionCode": "NNW",
            "level": "<3级"
          },
          "sunset": "日落 19:05"
        }
      }
    },
    {
      "id": "101160101",
      "province": "甘肃",
      "city": "兰州",
      "realtime": {
        "nameen": "lanzhou",
        "cityname": "兰州",
        "city": "101160101",
        "temp": "4.7",
        "tempf": "40.5",
        "WD": "东风",
        "wde": "E",
        "WS": "1级",
        "wse": "3km/h",
        "SD": "37%",
        "sd": "37%",
        "qy": "842",
        "njd": "14km",
        "time": "09:50",
        "rain": "0",
        "rain24h": "0",
        "aqi": "81",
        "aqi_pm25": "81",
        "weather": "多云",
        "weathere": "Cloudy",
        "weathercode": "d01",
        "limitnumber": "5和0",
        "date": "02月28日(星期五)"
      },
      "weather": {
        "day": {
          "date": "28日白天",
          "weather": "晴",
          "temp": "17",
          "tempUnit": "°C",
          "wind": {
            "direction": "无持续风向",
            "directionCode": "NNW",
            "level": "<3级"
          },
          "sunrise": "日出 07:37"
        },
        "night": {
          "date": "28日夜间",
          "weather": "多云",
          "temp": "0",
          "tempUnit": "°C",
          "wind": {
            "direction": "无持续风向",
            "directionCode": "NNW",
            "level": "<3级"
          },
          "sunset": "日落 18:57"
        }
      }
    },
    {
      "id": "101170101",
      "province": "宁夏",
      "city": "银川",
      "realtime": {
        "nameen": "yinchuan",
        "cityname": "银川",
        "city": "101170101",
        "temp": "0.5",
        "tempf": "32.9",
        "WD": "北风",
        "wde": "N",
        "WS": "2级",
        "wse": "8km/h",
        "SD": "34%",
        "sd": "34%",
        "qy": "885",
        "njd": "10km",
        "time": "09:55",
        "rain": "0",
        "rain24h": "0",
        "aqi": "79",
        "aqi_pm25": "79",
        "weather": "晴",
        "weathere": "Sunny",
        "weathercode": "d00",
        "limitnumber": "",
        "date": "02月28日(星期五)"
      },
      "weather": {
        "day": {
          "date": "28日白天",
          "weather": "多云",
          "temp": "12",
          "tempUnit": "°C",
          "wind": {
            "direction": "无持续风向",
            "directionCode": "NNW",
            "level": "<3级"
          },
          "sunrise": "日出 07:29"
        },
        "night": {
          "date": "28日夜间",
          "weather": "阴",
          "temp": "-1",
          "tempUnit": "°C",
          "wind": {
            "direction": "无持续风向",
            "directionCode": "NNW",
            "level": "<3级"
          },
          "sunset": "日落 18:45"
        }
      }
    },
    {
      "id": "101180101",
      "province": "河南",
      "city": "郑州",
      "realtime": {
        "nameen": "zhengzhou",
        "cityname": "郑州",
        "city": "101180101",
        "temp": "12.6",
        "tempf": "54.7",
        "WD": "东北风",
        "wde": "NE",
        "WS": "1级",
        "wse": "2km/h",
        "SD": "67%",
        "sd": "67%",
        "qy": "1003",
        "njd": "3km",
        "time": "09:50",
        "rain": "0",
        "rain24h": "0",
        "aqi": "170",
        "aqi_pm25": "170",
        "weather": "雾",
        "weathere": "Foggy",
        "weathercode": "d18",
        "limitnumber": "5和0",
        "date": "02月28日(星期五)"
      },
      "weather": {
        "day": {
          "date": "28日白天",
          "weather": "阴",
          "temp": "19",
          "tempUnit": "°C",
          "wind": {
            "direction": "东南风",
            "directionCode": "SE",
            "level": "<3级"
          },
          "sunrise": "日出 06:57"
        },
        "night": {
          "date": "28日夜间",
          "weather": "小雨",
          "temp": "11",
          "tempUnit": "°C",
          "wind": {
            "direction": "东南风",
            "directionCode": "SE",
            "level": "<3级"
          },
          "sunset": "日落 18:19"
        }
      }
    },
    {
      "id": "101190101",
      "province": "江苏",
      "city": "南京",
      "realtime": {
        "nameen": "nanjing",
        "cityname": "南京",
        "city": "101190101",
        "temp": "15",
        "tempf": "59",
        "WD": "东风",
        "wde": "E",
        "WS": "2级",
        "wse": "10km/h",
        "SD": "74%",
        "sd": "74%",
        "qy": "1013",
        "njd": "3km",
        "time": "09:50",
        "rain": "0",
        "rain24h": "0",
        "aqi": "93",
        "aqi_pm25": "93",
        "weather": "雾",
        "weathere": "Foggy",
        "weathercode": "d18",
        "limitnumber": "",
        "date": "02月28日(星期五)"
      },
      "weather": {
        "day": {
          "date": "28日白天",
          "weather": "多云",
          "temp": "21",
          "tempUnit": "°C",
          "wind": {
            "direction": "东南风",
            "directionCode": "SE",
            "level": "3-4级"
          },
          "sunrise": "日出 06:34"
        },
        "night": {
          "date": "28日夜间",
          "weather": "多云",
          "temp": "9",
          "tempUnit": "°C",
          "wind": {
            "direction": "东南风",
            "directionCode": "SE",
            "level": "3-4级"
          },
          "sunset": "日落 18:00"
        }
      }
    },
    {
      "id": "101200101",
      "province": "湖北",
      "city": "武汉",
      "realtime": {
        "nameen": "wuhan",
        "cityname": "武汉",
        "city": "101200101",
        "temp": "15.3",
        "tempf": "59.5",
        "WD": "东风",
        "wde": "E",
        "WS": "1级",
        "wse": "4km/h",
        "SD": "82%",
        "sd": "82%",
        "qy": "1012",
        "njd": "4km",
        "time": "09:50",
        "rain": "0",
        "rain24h": "0",
        "aqi": "73",
        "aqi_pm25": "73",
        "weather": "多云",
        "weathere": "Cloudy",
        "weathercode": "d01",
        "limitnumber": "单号限行",
        "date": "02月28日(星期五)"
      },
      "weather": {
        "day": {
          "date": "28日白天",
          "weather": "阴",
          "temp": "21",
          "tempUnit": "°C",
          "wind": {
            "direction": "无持续风向",
            "directionCode": "NNW",
            "level": "<3级"
          },
          "sunrise": "日出 06:51"
        },
        "night": {
          "date": "28日夜间",
          "weather": "阴",
          "temp": "12",
          "tempUnit": "°C",
          "wind": {
            "direction": "无持续风向",
            "directionCode": "NNW",
            "level": "<3级"
          },
          "sunset": "日落 18:19"
        }
      }
    },
    {
      "id": "101210101",
      "province": "浙江",
      "city": "杭州",
      "realtime": {
        "nameen": "hangzhou",
        "cityname": "杭州",
        "city": "101210101",
        "temp": "16.6",
        "tempf": "61.9",
        "WD": "南风",
        "wde": "S",
        "WS": "2级",
        "wse": "10km/h",
        "SD": "72%",
        "sd": "72%",
        "qy": "1013",
        "njd": "8km",
        "time": "09:50",
        "rain": "0",
        "rain24h": "0",
        "aqi": "46",
        "aqi_pm25": "46",
        "weather": "霾",
        "weathere": "haze",
        "weathercode": "d53",
        "limitnumber": "5和0",
        "date": "02月28日(星期五)"
      },
      "weather": {
        "day": {
          "date": "28日白天",
          "weather": "晴",
          "temp": "24",
          "tempUnit": "°C",
          "wind": {
            "direction": "东风",
            "directionCode": "E",
            "level": "4-5级"
          },
          "sunrise": "日出 06:27"
        },
        "night": {
          "date": "28日夜间",
          "weather": "多云",
          "temp": "10",
          "tempUnit": "°C",
          "wind": {
            "direction": "西南风",
            "directionCode": "SW",
            "level": "3-4级"
          },
          "sunset": "日落 17:56"
        }
      }
    },
    {
      "id": "101220101",
      "province": "安徽",
      "city": "合肥",
      "realtime": {
        "nameen": "hefei",
        "cityname": "合肥",
        "city": "101220101",
        "temp": "15.5",
        "tempf": "59.9",
        "WD": "东风",
        "wde": "E",
        "WS": "2级",
        "wse": "11km/h",
        "SD": "76%",
        "sd": "76%",
        "qy": "1009",
        "njd": "4km",
        "time": "09:55",
        "rain": "0",
        "rain24h": "0",
        "aqi": "74",
        "aqi_pm25": "74",
        "weather": "雾",
        "weathere": "Foggy",
        "weathercode": "d18",
        "limitnumber": "",
        "date": "02月28日(星期五)"
      },
      "weather": {
        "day": {
          "date": "28日白天",
          "weather": "阴",
          "temp": "21",
          "tempUnit": "°C",
          "wind": {
            "direction": "东南风",
            "directionCode": "SE",
            "level": "4-5级"
          },
          "sunrise": "日出 06:40"
        },
        "night": {
          "date": "28日夜间",
          "weather": "多云",
          "temp": "9",
          "tempUnit": "°C",
          "wind": {
            "direction": "南风",
            "directionCode": "S",
            "level": "<3级"
          },
          "sunset": "日落 18:07"
        }
      }
    },
    {
      "id": "101230101",
      "province": "福建",
      "city": "福州",
      "realtime": {
        "nameen": "fuzhou",
        "cityname": "福州",
        "city": "101230101",
        "temp": "14.4",
        "tempf": "57.9",
        "WD": "北风",
        "wde": "N",
        "WS": "1级",
        "wse": "4km/h",
        "SD": "100%",
        "sd": "100%",
        "qy": "1010",
        "njd": "4km",
        "time": "09:55",
        "rain": "0",
        "rain24h": "0",
        "aqi": "52",
        "aqi_pm25": "52",
        "weather": "雾",
        "weathere": "Foggy",
        "weathercode": "d18",
        "limitnumber": "",
        "date": "02月28日(星期五)"
      },
      "weather": {
        "day": {
          "date": "28日白天",
          "weather": "晴",
          "temp": "24",
          "tempUnit": "°C",
          "wind": {
            "direction": "东南风",
            "directionCode": "SE",
            "level": "<3级"
          },
          "sunrise": "日出 06:27"
        },
        "night": {
          "date": "28日夜间",
          "weather": "阴",
          "temp": "14",
          "tempUnit": "°C",
          "wind": {
            "direction": "东风",
            "directionCode": "E",
            "level": "<3级"
          },
          "sunset": "日落 18:03"
        }
      }
    },
    {
      "id": "101240101",
      "province": "江西",
      "city": "南昌",
      "realtime": {
        "nameen": "nanchang",
        "cityname": "南昌",
        "city": "101240101",
        "temp": "17.2",
        "tempf": "63",
        "WD": "东风",
        "wde": "E",
        "WS": "1级",
        "wse": "2km/h",
        "SD": "79%",
        "sd": "79%",
        "qy": "1012",
        "njd": "9km",
        "time": "09:50",
        "rain": "0",
        "rain24h": "0",
        "aqi": "55",
        "aqi_pm25": "55",
        "weather": "雾",
        "weathere": "Foggy",
        "weathercode": "d18",
        "limitnumber": "",
        "date": "02月28日(星期五)"
      },
      "weather": {
        "day": {
          "date": "28日白天",
          "weather": "多云",
          "temp": "24",
          "tempUnit": "°C",
          "wind": {
            "direction": "东南风",
            "directionCode": "SE",
            "level": "<3级"
          },
          "sunrise": "日出 06:43"
        },
        "night": {
          "date": "28日夜间",
          "weather": "多云",
          "temp": "12",
          "tempUnit": "°C",
          "wind": {
            "direction": "东风",
            "directionCode": "E",
            "level": "<3级"
          },
          "sunset": "日落 18:14"
        }
      }
    },
    {
      "id": "101250101",
      "province": "湖南",
      "city": "长沙",
      "realtime": {
        "nameen": "changsha",
        "cityname": "长沙",
        "city": "101250101",
        "temp": "15.4",
        "tempf": "59.7",
        "WD": "东南风",
        "wde": "SE",
        "WS": "2级",
        "wse": "9km/h",
        "SD": "90%",
        "sd": "90%",
        "qy": "1001",
        "njd": "5km",
        "time": "09:55",
        "rain": "0",
        "rain24h": "0",
        "aqi": "64",
        "aqi_pm25": "64",
        "weather": "雾",
        "weathere": "Foggy",
        "weathercode": "d18",
        "limitnumber": "",
        "date": "02月28日(星期五)"
      },
      "weather": {
        "day": {
          "date": "28日白天",
          "weather": "多云",
          "temp": "24",
          "tempUnit": "°C",
          "wind": {
            "direction": "西南风",
            "directionCode": "SW",
            "level": "<3级"
          },
          "sunrise": "日出 06:54"
        },
        "night": {
          "date": "28日夜间",
          "weather": "多云",
          "temp": "15",
          "tempUnit": "°C",
          "wind": {
            "direction": "南风",
            "directionCode": "S",
            "level": "<3级"
          },
          "sunset": "日落 18:26"
        }
      }
    },
    {
      "id": "101260101",
      "province": "贵州",
      "city": "贵阳",
      "realtime": {
        "nameen": "guiyang",
        "cityname": "贵阳",
        "city": "101260101",
        "temp": "11.9",
        "tempf": "53.4",
        "WD": "南风",
        "wde": "S",
        "WS": "1级",
        "wse": "4km/h",
        "SD": "83%",
        "sd": "83%",
        "qy": "876",
        "njd": "14km",
        "time": "09:55",
        "rain": "0",
        "rain24h": "0",
        "aqi": "34",
        "aqi_pm25": "34",
        "weather": "多云",
        "weathere": "Cloudy",
        "weathercode": "d01",
        "limitnumber": null,
        "date": "02月28日(星期五)"
      },
      "weather": {
        "day": {
          "date": "28日白天",
          "weather": "多云",
          "temp": "22",
          "tempUnit": "°C",
          "wind": {
            "direction": "南风",
            "directionCode": "S",
            "level": "<3级"
          },
          "sunrise": "日出 07:18"
        },
        "night": {
          "date": "28日夜间",
          "weather": "多云",
          "temp": "12",
          "tempUnit": "°C",
          "wind": {
            "direction": "南风",
            "directionCode": "S",
            "level": "3-4级"
          },
          "sunset": "日落 18:53"
        }
      }
    },
    {
      "id": "101270101",
      "province": "四川",
      "city": "成都",
      "realtime": {
        "nameen": "chengdu",
        "cityname": "成都",
        "city": "101270101",
        "temp": "9.8",
        "tempf": "49.6",
        "WD": "南风",
        "wde": "S",
        "WS": "1级",
        "wse": "3km/h",
        "SD": "89%",
        "sd": "89%",
        "qy": "956",
        "njd": "1km",
        "time": "09:50",
        "rain": "0",
        "rain24h": "0",
        "aqi": "82",
        "aqi_pm25": "82",
        "weather": "晴",
        "weathere": "Sunny",
        "weathercode": "d00",
        "limitnumber": "5和0",
        "date": "02月28日(星期五)"
      },
      "weather": {
        "day": {
          "date": "28日白天",
          "weather": "多云",
          "temp": "19",
          "tempUnit": "°C",
          "wind": {
            "direction": "北风",
            "directionCode": "N",
            "level": "<3级"
          },
          "sunrise": "日出 07:32"
        },
        "night": {
          "date": "28日夜间",
          "weather": "多云",
          "temp": "3",
          "tempUnit": "°C",
          "wind": {
            "direction": "北风",
            "directionCode": "N",
            "level": "<3级"
          },
          "sunset": "日落 19:00"
        }
      }
    },
    {
      "id": "101280101",
      "province": "广东",
      "city": "广州",
      "realtime": {
        "nameen": "guangzhou",
        "cityname": "广州",
        "city": "101280101",
        "temp": "20.5",
        "tempf": "68.9",
        "WD": "东风",
        "wde": "E",
        "WS": "1级",
        "wse": "3km/h",
        "SD": "83%",
        "sd": "83%",
        "qy": "1015",
        "njd": "7km",
        "time": "09:50",
        "rain": "0",
        "rain24h": "0",
        "aqi": "57",
        "aqi_pm25": "57",
        "weather": "多云",
        "weathere": "Cloudy",
        "weathercode": "d01",
        "limitnumber": "单号限行",
        "date": "02月28日(星期五)"
      },
      "weather": {
        "day": {
          "date": "28日白天",
          "weather": "多云",
          "temp": "26",
          "tempUnit": "°C",
          "wind": {
            "direction": "无持续风向",
            "directionCode": "NNW",
            "level": "<3级"
          },
          "sunrise": "日出 06:50"
        },
        "night": {
          "date": "28日夜间",
          "weather": "多云",
          "temp": "17",
          "tempUnit": "°C",
          "wind": {
            "direction": "无持续风向",
            "directionCode": "NNW",
            "level": "<3级"
          },
          "sunset": "日落 18:29"
        }
      }
    },
    {
      "id": "101290101",
      "province": "云南",
      "city": "昆明",
      "realtime": {
        "nameen": "kunming",
        "cityname": "昆明",
        "city": "101290101",
        "temp": "14.9",
        "tempf": "58.8",
        "WD": "西南风",
        "wde": "SW",
        "WS": "3级",
        "wse": "14km/h",
        "SD": "40%",
        "sd": "40%",
        "qy": "812",
        "njd": "21km",
        "time": "09:50",
        "rain": "0",
        "rain24h": "0",
        "aqi": "48",
        "aqi_pm25": "48",
        "weather": "晴",
        "weathere": "Sunny",
        "weathercode": "d00",
        "limitnumber": "",
        "date": "02月28日(星期五)"
      },
      "weather": {
        "day": {
          "date": "28日白天",
          "weather": "晴",
          "temp": "22",
          "tempUnit": "°C",
          "wind": {
            "direction": "西南风",
            "directionCode": "SW",
            "level": "3-4级"
          },
          "sunrise": "日出 07:32"
        },
        "night": {
          "date": "28日夜间",
          "weather": "晴",
          "temp": "8",
          "tempUnit": "°C",
          "wind": {
            "direction": "无持续风向",
            "directionCode": "NNW",
            "level": "<3级"
          },
          "sunset": "日落 19:09"
        }
      }
    },
    {
      "id": "101300101",
      "province": "广西",
      "city": "南宁",
      "realtime": {
        "nameen": "nanning",
        "cityname": "南宁",
        "city": "101300101",
        "temp": "19.4",
        "tempf": "66.9",
        "WD": "南风",
        "wde": "S",
        "WS": "2级",
        "wse": "10km/h",
        "SD": "90%",
        "sd": "90%",
        "qy": "999",
        "njd": "6km",
        "time": "09:50",
        "rain": "0",
        "rain24h": "0",
        "aqi": "58",
        "aqi_pm25": "58",
        "weather": "阴",
        "weathere": "Overcast",
        "weathercode": "d02",
        "limitnumber": "",
        "date": "02月28日(星期五)"
      },
      "weather": {
        "day": {
          "date": "28日白天",
          "weather": "多云",
          "temp": "23",
          "tempUnit": "°C",
          "wind": {
            "direction": "南风",
            "directionCode": "S",
            "level": "<3级"
          },
          "sunrise": "日出 07:09"
        },
        "night": {
          "date": "28日夜间",
          "weather": "阴",
          "temp": "17",
          "tempUnit": "°C",
          "wind": {
            "direction": "南风",
            "directionCode": "S",
            "level": "<3级"
          },
          "sunset": "日落 18:48"
        }
      }
    },
    {
      "id": "101310101",
      "province": "海南",
      "city": "海口",
      "realtime": {
        "nameen": "haikou",
        "cityname": "海口",
        "city": "101310101",
        "temp": "21.2",
        "tempf": "70.2",
        "WD": "东风",
        "wde": "E",
        "WS": "2级",
        "wse": "6km/h",
        "SD": "86%",
        "sd": "86%",
        "qy": "1010",
        "njd": "16km",
        "time": "09:55",
        "rain": "0",
        "rain24h": "0",
        "aqi": "25",
        "aqi_pm25": "25",
        "weather": "雾",
        "weathere": "Foggy",
        "weathercode": "d18",
        "limitnumber": "",
        "date": "02月28日(星期五)"
      },
      "weather": {
        "day": {
          "date": "28日白天",
          "weather": "多云",
          "temp": "29",
          "tempUnit": "°C",
          "wind": {
            "direction": "东南风",
            "directionCode": "SE",
            "level": "3-4级"
          },
          "sunrise": "日出 06:59"
        },
        "night": {
          "date": "28日夜间",
          "weather": "多云",
          "temp": "19",
          "tempUnit": "°C",
          "wind": {
            "direction": "无持续风向",
            "directionCode": "NNW",
            "level": "<3级"
          },
          "sunset": "日落 18:42"
        }
      }
    },
    {
      "id": "101320101",
      "province": "香港",
      "city": "香港",
      "realtime": {
        "nameen": "hongkong",
        "cityname": "香港",
        "city": "101320101",
        "temp": "18.9",
        "tempf": "66",
        "WD": "微风",
        "wde": "NWW",
        "WS": "2级",
        "wse": "5km/h",
        "SD": "90%",
        "sd": "90%",
        "qy": "999",
        "njd": "14km",
        "time": "10:00",
        "rain": "0",
        "rain24h": "0",
        "aqi": "43",
        "aqi_pm25": "43",
        "weather": "多云",
        "weathere": "Cloudy",
        "weathercode": "d01",
        "limitnumber": "",
        "date": "02月28日(星期五)"
      },
      "weather": {
        "day": {
          "date": "28日白天",
          "weather": "多云",
          "temp": "24",
          "tempUnit": "°C",
          "wind": {
            "direction": "无持续风向",
            "directionCode": "NNW",
            "level": "<3级"
          },
          "sunrise": "日出 06:45"
        },
        "night": {
          "date": "28日夜间",
          "weather": "多云",
          "temp": "17",
          "tempUnit": "°C",
          "wind": {
            "direction": "无持续风向",
            "directionCode": "NNW",
            "level": "<3级"
          },
          "sunset": "日落 18:26"
        }
      }
    },
    {
      "id": "101330101",
      "province": "澳门",
      "city": "澳门",
      "realtime": {
        "nameen": "macao",
        "cityname": "澳门",
        "city": "101330101",
        "temp": "20.2",
        "tempf": "68.4",
        "WD": "微风",
        "wde": "NWW",
        "WS": "1级",
        "wse": "1km/h",
        "SD": "82%",
        "sd": "82%",
        "qy": "1006",
        "njd": "7km",
        "time": "10:00",
        "rain": "0",
        "rain24h": "0",
        "aqi": "49",
        "aqi_pm25": "49",
        "weather": "阴",
        "weathere": "Overcast",
        "weathercode": "d02",
        "limitnumber": "",
        "date": "02月28日(星期五)"
      },
      "weather": {
        "day": {
          "date": "28日白天",
          "weather": "晴",
          "temp": "23",
          "tempUnit": "°C",
          "wind": {
            "direction": "无持续风向",
            "directionCode": "NNW",
            "level": "<3级"
          },
          "sunrise": "日出 06:48"
        },
        "night": {
          "date": "28日夜间",
          "weather": "多云",
          "temp": "18",
          "tempUnit": "°C",
          "wind": {
            "direction": "无持续风向",
            "directionCode": "NNW",
            "level": "<3级"
          },
          "sunset": "日落 18:28"
        }
      }
    },
    {
      "id": "101340101",
      "province": "台湾",
      "city": "台北",
      "realtime": {
        "nameen": "taibeixian",
        "cityname": "台北",
        "city": "101340101",
        "temp": "22.4",
        "tempf": "72.3",
        "WD": "微风",
        "wde": "NWW",
        "WS": "1级",
        "wse": "1km/h",
        "SD": "75%",
        "sd": "75%",
        "qy": "1007",
        "njd": "0km",
        "time": "10:00",
        "rain": "0",
        "rain24h": "0",
        "aqi": "99",
        "aqi_pm25": "99",
        "weather": "晴",
        "weathere": "Sunny",
        "weathercode": "d00",
        "limitnumber": "",
        "date": "02月28日(星期五)"
      },
      "weather": {
        "day": {
          "date": "28日白天",
          "weather": "晴",
          "temp": "23",
          "tempUnit": "°C",
          "wind": {
            "direction": "无持续风向",
            "directionCode": "NNW",
            "level": "<3级"
          },
          "sunrise": "日出 06:18"
        },
        "night": {
          "date": "28日夜间",
          "weather": "多云",
          "temp": "15",
          "tempUnit": "°C",
          "wind": {
            "direction": "无持续风向",
            "directionCode": "NNW",
            "level": "<3级"
          },
          "sunset": "日落 17:54"
        }
      }
    }
  ]
}